README.md
setup.py
pyRadialPlot/FTradialplot.py
pyRadialPlot/__init__.py
pyRadialPlot/radialplot.py
pyRadialPlot/utilities.py
pyRadialPlot.egg-info/PKG-INFO
pyRadialPlot.egg-info/SOURCES.txt
pyRadialPlot.egg-info/dependency_links.txt
pyRadialPlot.egg-info/not-zip-safe
pyRadialPlot.egg-info/top_level.txt