Metadata-Version: 1.0
Name: pyRadialPlot
Version: 0.3
Summary: Radial Plot using python and matplotlib
Home-page: http://github.com/rbeucher/pyRadialPlot
Author: Romain Beucher
Author-email: romain.beucher@unimelb.edu.au
License: MIT
Platform: UNKNOWN
